templitz.py
templitz-2017.10.3.dist-info/entry_points.txt
templitz-2017.10.3.dist-info/LICENSE
templitz-2017.10.3.dist-info/WHEEL
templitz-2017.10.3.dist-info/METADATA
templitz-2017.10.3.dist-info/RECORD
