Metadata-Version: 1.2
Name: templitz
Version: 2017.10.3
Summary: Generate new files from templates. 
Home-page: https://github.com/cjrh/templitz
License: UNKNOWN
Keywords: template bootstrap
Author: Caleb Hattingh
Author-email: caleb.hattingh@gmail.com
Classifier: License :: OSI Approved :: Apache Software License
Classifier: Natural Language :: English
Classifier: Programming Language :: Python
Classifier: Programming Language :: Python :: 2.7
Classifier: Programming Language :: Python :: 3.4
Classifier: Programming Language :: Python :: 3.5
Classifier: Programming Language :: Python :: 3.6
Classifier: Operating System :: OS Independent
Requires-Dist: cjrh_template
Requires-Dist: biodome
